docments/__init__.py
docments/_nbdev.py
docments/core.py
docments-0.0.1.dist-info/LICENSE
docments-0.0.1.dist-info/METADATA
docments-0.0.1.dist-info/WHEEL
docments-0.0.1.dist-info/entry_points.txt
docments-0.0.1.dist-info/top_level.txt
docments-0.0.1.dist-info/RECORD
