Metadata-Version: 2.1
Name: docments
Version: 0.0.1
Summary: docments
Home-page: https://github.com/fastai/docments/tree/master/
Author: Jeremy Howard
Author-email: j@fast.ai
License: Apache Software License 2.0
Keywords: documentation python nbdev fastai comments
Platform: UNKNOWN
Classifier: Development Status :: 3 - Alpha
Classifier: Intended Audience :: Developers
Classifier: Natural Language :: English
Classifier: Programming Language :: Python :: 3.6
Classifier: Programming Language :: Python :: 3.7
Classifier: Programming Language :: Python :: 3.8
Classifier: License :: OSI Approved :: Apache Software License
Requires-Python: >=3.6
Requires-Dist: fastcore (>=1.3.8)
